sarenza_automation_core/__init__.py
sarenza_automation_core/driver_factory.py
sarenza_automation_core/pages/base_page.py
sarenza_automation_core/utils/__init__.py
sarenza_automation_core/utils/assertion_helper.py
sarenza_automation_core/utils/browser_console_helper.py
sarenza_automation_core/utils/config_reader_helper.py
sarenza_automation_core/utils/email_generator_helper.py
sarenza_automation_core/utils/local_storage_helper.py
sarenza_automation_core/utils/logger.py
sarenza_automation_core/utils/schemas.py
sarenza_automation_core/utils/translation_handler_helper.py
sarenza_automation_core/utils/user_information_helper.py
sarenza_automation_core-0.1.0.1.1.dist-info/METADATA
sarenza_automation_core-0.1.0.1.1.dist-info/WHEEL
sarenza_automation_core-0.1.0.1.1.dist-info/RECORD
