Metadata-Version: 2.3
Name: sarenza-automation-core
Version: 0.1.0.1.1
Summary: Non regression test automation framework core
Author: QA Sarenza
Author-email: qa_srz@sarenza.com
Requires-Python: >=3.11,<4.0
Classifier: Programming Language :: Python :: 3
Classifier: Programming Language :: Python :: 3.11
Classifier: Programming Language :: Python :: 3.12
Classifier: Programming Language :: Python :: 3.13
Requires-Dist: allure-behave (==2.13.2)
Requires-Dist: allure-python-commons (==2.13.2)
Requires-Dist: appium-python-client (>=4.5.1,<5.0.0)
Requires-Dist: faker (>=37.4.2,<38.0.0)
Requires-Dist: loguru (>=0.7.3,<0.8.0)
Requires-Dist: pydantic (==2.10.3)
Requires-Dist: python-dotenv (>=1.1.1,<2.0.0)
Requires-Dist: selenium (==4.26.0)
Requires-Dist: webdriver-manager (==4.0.2)
